extras/__init__.py
basic_example-0.0.1.dist-info/METADATA
basic_example-0.0.1.dist-info/WHEEL
basic_example-0.0.1.dist-info/top_level.txt
basic_example-0.0.1.dist-info/RECORD
